{
  "attributes": [
    {
      "allow_nil?": false,
      "default": "fragment(\"gen_random_uuid()\")",
      "generated?": false,
      "precision": null,
      "primary_key?": true,
      "references": null,
      "scale": null,
      "size": null,
      "source": "id",
      "type": "uuid"
    },
    {
      "allow_nil?": false,
      "default": "nil",
      "generated?": false,
      "precision": null,
      "primary_key?": false,
      "references": null,
      "scale": null,
      "size": null,
      "source": "decision",
      "type": "text"
    },
    {
      "allow_nil?": true,
      "default": "nil",
      "generated?": false,
      "precision": null,
      "primary_key?": false,
      "references": null,
      "scale": null,
      "size": null,
      "source": "reason",
      "type": "text"
    },
    {
      "allow_nil?": true,
      "default": "nil",
      "generated?": false,
      "precision": null,
      "primary_key?": false,
      "references": null,
      "scale": null,
      "size": null,
      "source": "reason_code",
      "type": "text"
    },
    {
      "allow_nil?": true,
      "default": "nil",
      "generated?": false,
      "precision": null,
      "primary_key?": false,
      "references": null,
      "scale": null,
      "size": null,
      "source": "feedback_scope",
      "type": "text"
    },
    {
      "allow_nil?": true,
      "default": "nil",
      "generated?": false,
      "precision": null,
      "primary_key?": false,
      "references": null,
      "scale": null,
      "size": null,
      "source": "source_feedback_category",
      "type": "text"
    },
    {
      "allow_nil?": true,
      "default": "nil",
      "generated?": false,
      "precision": null,
      "primary_key?": false,
      "references": null,
      "scale": null,
      "size": null,
      "source": "recorded_at",
      "type": "utc_datetime"
    },
    {
      "allow_nil?": false,
      "default": "%{}",
      "generated?": false,
      "precision": null,
      "primary_key?": false,
      "references": null,
      "scale": null,
      "size": null,
      "source": "metadata",
      "type": "map"
    },
    {
      "allow_nil?": false,
      "default": "fragment(\"(now() AT TIME ZONE 'utc')\")",
      "generated?": false,
      "precision": null,
      "primary_key?": false,
      "references": null,
      "scale": null,
      "size": null,
      "source": "inserted_at",
      "type": "utc_datetime_usec"
    },
    {
      "allow_nil?": false,
      "default": "fragment(\"(now() AT TIME ZONE 'utc')\")",
      "generated?": false,
      "precision": null,
      "primary_key?": false,
      "references": null,
      "scale": null,
      "size": null,
      "source": "updated_at",
      "type": "utc_datetime_usec"
    },
    {
      "allow_nil?": false,
      "default": "nil",
      "generated?": false,
      "precision": null,
      "primary_key?": false,
      "references": {
        "deferrable": false,
        "destination_attribute": "id",
        "destination_attribute_default": null,
        "destination_attribute_generated": null,
        "index?": false,
        "match_type": null,
        "match_with": null,
        "multitenancy": {
          "attribute": null,
          "global": null,
          "strategy": null
        },
        "name": "source_filter_feedback_filter_id_fkey",
        "on_delete": "delete",
        "on_update": null,
        "primary_key?": true,
        "schema": "public",
        "table": "procurement_source_search_filters"
      },
      "scale": null,
      "size": null,
      "source": "source_search_filter_id",
      "type": "uuid"
    },
    {
      "allow_nil?": false,
      "default": "nil",
      "generated?": false,
      "precision": null,
      "primary_key?": false,
      "references": {
        "deferrable": false,
        "destination_attribute": "id",
        "destination_attribute_default": null,
        "destination_attribute_generated": null,
        "index?": false,
        "match_type": null,
        "match_with": null,
        "multitenancy": {
          "attribute": null,
          "global": null,
          "strategy": null
        },
        "name": "source_filter_feedback_finding_id_fkey",
        "on_delete": "delete",
        "on_update": null,
        "primary_key?": true,
        "schema": "public",
        "table": "acquisition_findings"
      },
      "scale": null,
      "size": null,
      "source": "finding_id",
      "type": "uuid"
    }
  ],
  "base_filter": null,
  "check_constraints": [],
  "create_table_options": null,
  "custom_indexes": [
    {
      "all_tenants?": false,
      "concurrently": false,
      "error_fields": [
        "source_search_filter_id",
        "decision"
      ],
      "fields": [
        {
          "type": "atom",
          "value": "source_search_filter_id"
        },
        {
          "type": "atom",
          "value": "decision"
        }
      ],
      "include": null,
      "message": null,
      "name": null,
      "nulls_distinct": true,
      "prefix": null,
      "table": null,
      "unique": false,
      "using": null,
      "where": null
    },
    {
      "all_tenants?": false,
      "concurrently": false,
      "error_fields": [
        "reason_code"
      ],
      "fields": [
        {
          "type": "atom",
          "value": "reason_code"
        }
      ],
      "include": null,
      "message": null,
      "name": null,
      "nulls_distinct": true,
      "prefix": null,
      "table": null,
      "unique": false,
      "using": null,
      "where": null
    },
    {
      "all_tenants?": false,
      "concurrently": false,
      "error_fields": [
        "recorded_at"
      ],
      "fields": [
        {
          "type": "atom",
          "value": "recorded_at"
        }
      ],
      "include": null,
      "message": null,
      "name": null,
      "nulls_distinct": true,
      "prefix": null,
      "table": null,
      "unique": false,
      "using": null,
      "where": null
    }
  ],
  "custom_statements": [],
  "has_create_action": true,
  "hash": "F79143E8324A535838E957755D66C1E2965FC691DE442D08994C1EC3F72697D5",
  "identities": [
    {
      "all_tenants?": false,
      "base_filter": null,
      "index_name": "source_filter_feedback_unique_idx",
      "keys": [
        {
          "type": "atom",
          "value": "source_search_filter_id"
        },
        {
          "type": "atom",
          "value": "finding_id"
        },
        {
          "type": "atom",
          "value": "decision"
        }
      ],
      "name": "unique_filter_finding_decision",
      "nils_distinct?": true,
      "where": null
    }
  ],
  "multitenancy": {
    "attribute": null,
    "global": null,
    "strategy": null
  },
  "repo": "Elixir.GnomeGarden.Repo",
  "schema": null,
  "table": "procurement_source_search_filter_feedback"
}
